fyle_integrations_platform_connector/__init__.py
fyle_integrations_platform_connector/fyle_integrations_platform_connector.py
fyle_integrations_platform_connector/apis/__init__.py
fyle_integrations_platform_connector/apis/base.py
fyle_integrations_platform_connector/apis/categories.py
fyle_integrations_platform_connector/apis/corporate_card_transactions.py
fyle_integrations_platform_connector/apis/corporate_cards.py
fyle_integrations_platform_connector/apis/cost_centers.py
fyle_integrations_platform_connector/apis/departments.py
fyle_integrations_platform_connector/apis/dependent_fields.py
fyle_integrations_platform_connector/apis/employees.py
fyle_integrations_platform_connector/apis/expense_custom_fields.py
fyle_integrations_platform_connector/apis/expenses.py
fyle_integrations_platform_connector/apis/files.py
fyle_integrations_platform_connector/apis/merchants.py
fyle_integrations_platform_connector/apis/org_settings.py
fyle_integrations_platform_connector/apis/projects.py
fyle_integrations_platform_connector/apis/reimbursements.py
fyle_integrations_platform_connector/apis/reports.py
fyle_integrations_platform_connector/apis/subscriptions.py
fyle_integrations_platform_connector/apis/tax_groups.py
migrations/__init__.py
fyle_integrations_platform_connector-2.9.0.dist-info/METADATA
fyle_integrations_platform_connector-2.9.0.dist-info/WHEEL
fyle_integrations_platform_connector-2.9.0.dist-info/top_level.txt
fyle_integrations_platform_connector-2.9.0.dist-info/RECORD
