Metadata-Version: 2.4
Name: fyle-integrations-platform-connector
Version: 2.9.0
Summary: A common platform connector for all the Fyle Integrations to interact with Fyle Platform APIs
Home-page: https://github.com/fylein/fyle-integrations-platform-connector
Author: Shwetabh Kumar
Author-email: shwetabh.kumar@fyle.in
License: MIT
Keywords: fyle,api,python,integration,platform,connector
Classifier: Topic :: Internet :: WWW/HTTP
Classifier: Intended Audience :: Developers
Classifier: Programming Language :: Python :: 3
Classifier: License :: OSI Approved :: MIT License
Classifier: Operating System :: OS Independent
Requires-Dist: fyle_accounting_mappings>=1.25.0
Requires-Dist: fyle>=v0.36.1
Dynamic: author
Dynamic: author-email
Dynamic: classifier
Dynamic: description
Dynamic: description-content-type
Dynamic: home-page
Dynamic: keywords
Dynamic: license
Dynamic: requires-dist
Dynamic: summary
